g4ppyy/SI.py
g4ppyy/__bindings.py
g4ppyy/__init__.py
g4ppyy/_base_visualiser.py
g4ppyy/_bindings.py
g4ppyy/_categories.py
g4ppyy/_k3d_visualiser.py
g4ppyy/_lazy_loader.py
g4ppyy/_managers.py
g4ppyy/_mpl_visualiser.py
g4ppyy/_si_units.py
g4ppyy/_visualisers.py
g4ppyy/base_visualiser.py
g4ppyy/binding.py
g4ppyy/destructor.py
g4ppyy/helpers.py
g4ppyy/k3d_visualiser.py
g4ppyy/lazy_loader.py
g4ppyy/macros.py
g4ppyy/magic.py
g4ppyy/managers.py
g4ppyy/mpl_visualiser.py
g4ppyy/register.py
g4ppyy/run.py
g4ppyy/si_units.py
g4ppyy/vis.py
g4ppyy/builder/__init__.py
g4ppyy/builder/actions.py
g4ppyy/builder/generators.py
g4ppyy/builder/worlds.py
g4ppyy/macros/interactive_vis.mac
g4ppyy/macros/jupyter_quiet.mac
g4ppyy/macros/jupyter_vis.mac
g4ppyy/macros/mpljupyter_vis.mac
g4ppyy-0.1.0.dist-info/LICENSE
g4ppyy-0.1.0.dist-info/METADATA
g4ppyy-0.1.0.dist-info/WHEEL
g4ppyy-0.1.0.dist-info/top_level.txt
g4ppyy-0.1.0.dist-info/RECORD
