Metadata-Version: 2.1
Name: g4ppyy
Version: 0.1.0
Summary: Python binding helper tools for G4 and CPPYY
Home-page: https://github.com/patrickstowell/G4ppyy
Author: Patrick Stowell
Author-email: p.stowell@sheffield.ac.uk
Classifier: Programming Language :: Python :: 3
Classifier: License :: OSI Approved :: MIT License
Classifier: Operating System :: OS Independent
Requires-Python: >=3.9
License-File: LICENSE
Requires-Dist: numpy
Requires-Dist: k3d
Requires-Dist: matplotlib
